[{"slug":"coffee","title":"Кофе","phrases":[]},{"slug":"water","title":"вода","phrases":[]},{"slug":"juice","title":"Сок","phrases":[]},{"slug":"tea","title":"Чай","phrases":[]},{"slug":"grape-juice","title":"Виноградный сок","phrases":[]},{"slug":"milk","title":"Молоко","phrases":[]},{"slug":"milkshake","title":"Молочный коктейль","phrases":[]},{"slug":"orange-juice","title":"апельсиновый сок","phrases":[]},{"slug":"apple-juice","title":"яблочный сок","phrases":[]},{"slug":"pineapple-juice","title":"Ананасовый сок","phrases":[]},{"slug":"lemonade","title":"Лимонад","phrases":[]},{"slug":"coke","title":"коксовый","phrases":[]},{"slug":"soda","title":"содовый","phrases":[]},{"slug":"frappe","title":"фраппе","phrases":[]},{"slug":"smoothie","title":"льстец","phrases":[]},{"slug":"iced-tea","title":"Чай со льдом","phrases":[]},{"slug":"hot-chocolate","title":"Горячий шоколад","phrases":[]},{"slug":"mineral-water","title":"Минеральная вода","phrases":[]}]