[{"slug":"protective-mask","title":"Beskyttelsesmaske","phrases":[]},{"slug":"stay-home","title":"Bli hjemme","phrases":[]},{"slug":"toilet-paper","title":"Toalettpapir","phrases":[]},{"slug":"sprayer","title":"Sprøyter","phrases":[]},{"slug":"disinfectant","title":"desinfiserende","phrases":[]},{"slug":"thermometer","title":"Termometer","phrases":[]},{"slug":"coughing","title":"hoste","phrases":[]},{"slug":"medical-assistance","title":"Medisinsk assistanse","phrases":[]},{"slug":"hand-sanitizer","title":"Hånddesinfeksjonsmiddel","phrases":[]},{"slug":"gloves","title":"hansker","phrases":[]},{"slug":"social-distancing","title":"Sosial distansering","phrases":[]},{"slug":"mouth-mask","title":"Munnmaske","phrases":[]},{"slug":"pandemic","title":"Pandemi","phrases":[]},{"slug":"working-at-home","title":"Jobber hjemme","phrases":[]},{"slug":"wet-wipes","title":"Våtservietter","phrases":[]},{"slug":"quarantine","title":"Karantene","phrases":[]},{"slug":"first-aid-kit","title":"Førstehjelpsskrin","phrases":[]},{"slug":"fitness","title":"Fitness","phrases":[]},{"slug":"e-learning","title":"E-læring","phrases":[]},{"slug":"virus","title":"Virus","phrases":[]},{"slug":"cleaning","title":"Rengjøring","phrases":[]}]