[{"slug":"one","title":"ูุงุญุฏ","phrases":[{"type":"โ","phrase":"ูุฃุชู ูุจู ุงุซููู."},{"type":"โ","phrase":"ูุฃุชู ุงููุฑุก ุจุนุฏ ุงูุตูุฑ."},{"type":"๐","phrase":"ุฃุฑูุฏ ูุงุญุฏ."}]},{"slug":"two","title":"ุงุซูุงู","phrases":[{"type":"โ","phrase":"ูุฃุชู ุงุซูุงู ูุจู ุซูุงุซุฉ."},{"type":"โ","phrase":"ูุฃุชู ุงุซูุงู ุจุนุฏ ุงูุขุฎุฑ."},{"type":"๐","phrase":"ุงุฑูุฏ ุงุซูุชูู."}]},{"slug":"three","title":"ุซูุงุซุฉ","phrases":[{"type":"โ","phrase":"ุซูุงุซุฉ ูุฃุชู ูุจู ุฃุฑุจุนุฉ."},{"type":"โ","phrase":"ุซูุงุซุฉ ูุฃุชู ุจุนุฏ ุงุซููู."},{"type":"๐","phrase":"ุงุฑูุฏ ุซูุงุซุฉ."}]},{"slug":"four","title":"ุฃุฑุจุนุฉ","phrases":[{"type":"โ","phrase":"ุฃุฑุจุนุฉ ุชุฃุชู ูุจู ุงูุฎุงูุณุฉ."},{"type":"โ","phrase":"ูุฃุชู ุฃุฑุจุนุฉ ุจุนุฏ ุซูุงุซุฉ."},{"type":"๐","phrase":"ุงุฑูุฏ ุงุฑุจุน."}]},{"slug":"five","title":"ุฎูุณุฉ","phrases":[{"type":"โ","phrase":"ุฎูุณุฉ ูุฃุชู ูุจู ุณุชุฉ."},{"type":"โ","phrase":"ุฎูุณุฉ ูุฃุชู ุจุนุฏ ุฃุฑุจุนุฉ."},{"type":"๐","phrase":"ุงุฑูุฏ ุฎูุณุฉ."}]},{"slug":"six","title":"ุณุชุฉ","phrases":[{"type":"โ","phrase":"ูุฃุชู ุณุชุฉ ูุจู ุณุจุนุฉ."},{"type":"โ","phrase":"ูุฃุชู ุณุชุฉ ุจุนุฏ ุฎูุณุฉ."},{"type":"๐","phrase":"ุงุฑูุฏ ุงุตูุงุญ."}]},{"slug":"seven","title":"ุณุจุนุฉ","phrases":[{"type":"โ","phrase":"ูุฃุชู ุณุจุนุฉ ูุจู ุซูุงููุฉ."},{"type":"โ","phrase":"ุณุจุนุฉ ุชุฃุชู ุจุนุฏ ุงูุณุงุฏุณุฉ."},{"type":"๐","phrase":"ุงุฑูุฏ ุณุจุนุฉ."}]},{"slug":"eight","title":"ุซูุงููุฉ","phrases":[{"type":"โ","phrase":"ุซูุงููุฉ ุชุฃุชู ูุจู ุงูุณุงุนุฉ ุงูุชุงุณุนุฉ."},{"type":"โ","phrase":"ุซูุงููุฉ ุชุฃุชู ุจุนุฏ ุงูุณุงุจุนุฉ."},{"type":"๐","phrase":"ุงุฑูุฏ ุซูุงููุฉ."}]},{"slug":"nine","title":"ุชุณุน","phrases":[{"type":"โ","phrase":"ุชุณุนุฉ ูุฃุชู ูุจู ุงูุนุงุดุฑุฉ."},{"type":"โ","phrase":"ุชุณุนุฉ ูุฃุชู ุจุนุฏ ุซูุงููุฉ."},{"type":"๐","phrase":"ุงุฑูุฏ ุชุณุนุฉ."}]},{"slug":"ten","title":"ุนุดุฑุฉ","phrases":[{"type":"โ","phrase":"ุนุดุฑุฉ ุชุฃุชู ูุจู ุงูุญุงุฏูุฉ ุนุดุฑุฉ."},{"type":"โ","phrase":"ูุฃุชู ุนุดุฑุฉ ุจุนุฏ ุชุณุนุฉ."},{"type":"๐","phrase":"ุงุฑูุฏ ุนุดุฑุฉ."}]},{"slug":"eleven","title":"ุฃุญุฏ ุนุดุฑ","phrases":[{"type":"โ","phrase":"ูุฃุชู ุฃุญุฏ ุนุดุฑ ูุจู ุงูุซุงูุซุฉ ุนุดุฑ."},{"type":"โ","phrase":"ูุฃุชู ุฃุญุฏ ุนุดุฑ ุจุนุฏ ุนุดุฑุฉ."},{"type":"๐","phrase":"ุฃุฑูุฏ ุฃุญุฏ ุนุดุฑ."}]},{"slug":"twenty","title":"ุนุดุฑูู","phrases":[{"type":"๐ข","phrase":"ูููููู ุงูุนุฏ ุญุชู ุนุดุฑูู."}]},{"slug":"thirty","title":"ุซูุงุซูู","phrases":[{"type":"๐ข","phrase":"ูููููู ุงูุนุฏ ุญุชู ุซูุงุซูู."}]},{"slug":"forty","title":"ุฃุฑุจุนูู","phrases":[{"type":"๐ข","phrase":"ูููููู ุงูุนุฏ ุญุชู ุฃุฑุจุนูู."}]},{"slug":"fifty","title":"ุฎูุณูู","phrases":[{"type":"๐ข","phrase":"ูููููู ุงูุนุฏ ุญุชู ุฎูุณูู."}]},{"slug":"hundred","title":"ูุงุฆุฉ","phrases":[{"type":"๐ข","phrase":"ูููููู ุงูุนุฏ ุญุชู ูุงุฆุฉ."}]},{"slug":"thousand","title":"ุฃูู","phrases":[{"type":"๐ข","phrase":"ูููููู ุงูุนุฏ ุญุชู ุฃูู."}]},{"slug":"calculator","title":"ุขูุฉ ุญุงุณุจุฉ","phrases":[{"type":"๐ฉ","phrase":"ุฃุฑูุฏ ุงุณุชุฎุฏุงู ุขูุฉ ุญุงุณุจุฉ."},{"type":"๐งฎ","phrase":"ูู ููููู ุฃู ุชุนูููู ููููุฉ ุงุณุชุฎุฏุงู ุงูุขูุฉ ุงูุญุงุณุจุฉุ"},{"type":"๐","phrase":"ูู ูููููู ุชุญุถูุฑ ุงูุขูุฉ ุงูุญุงุณุจุฉ ุงูุฎุงุตุฉ ุจูุ"}]}]