[{"slug":"apple","title":"แอปเปิ้ล","phrases":[]},{"slug":"watermelon","title":"แตงโม","phrases":[]},{"slug":"orange","title":"ส้ม","phrases":[]},{"slug":"strawberry","title":"สตรอเบอร์รี่","phrases":[]},{"slug":"grape","title":"องุ่น","phrases":[]},{"slug":"cherry","title":"เชอร์รี่","phrases":[]},{"slug":"mango","title":"มะม่วง","phrases":[]},{"slug":"guava","title":"ฝรั่ง","phrases":[]},{"slug":"banana","title":"กล้วย","phrases":[]},{"slug":"pomegranate","title":"ทับทิม","phrases":[]},{"slug":"raspberry","title":"ราสเบอร์รี่","phrases":[]},{"slug":"papaya","title":"มะละกอ","phrases":[]},{"slug":"kiwi","title":"กีวี่","phrases":[]},{"slug":"pineapple","title":"สัปปะรด","phrases":[]},{"slug":"lemon","title":"มะนาว","phrases":[]},{"slug":"apricot","title":"แอปริคอท","phrases":[]},{"slug":"dragon-fruit","title":"แก้วมังกร","phrases":[]},{"slug":"peach","title":"ลูกพีช","phrases":[]},{"slug":"avocado","title":"อาโวคาโด","phrases":[]},{"slug":"fig","title":"รูปที่","phrases":[]},{"slug":"lemon","title":"มะนาว","phrases":[]},{"slug":"lychee","title":"ลิ้นจี่","phrases":[]},{"slug":"passion-fruit","title":"เสาวรส","phrases":[]},{"slug":"blueberry","title":"บลูเบอร์รี่","phrases":[]},{"slug":"coconut","title":"มะพร้าว","phrases":[]}]