[{"slug":"cat","title":"පූසා","phrases":[{"type":"👀","phrase":"මම පූසෙක් දැක්කා."},{"type":"🔊","phrase":"බළලෙකු කරන ශබ්දය කුමක්ද?"}]},{"slug":"dog","title":"බල්ලා","phrases":[{"type":"👀","phrase":"මම බල්ලෙක් දැක්කා."}]},{"slug":"fish","title":"මාළු","phrases":[]},{"slug":"rabbit","title":"හාවා","phrases":[]},{"slug":"butterfly","title":"සමනලයා","phrases":[{"type":"❤️","phrase":"මම සමනලුන්ට කැමතියි."}]},{"slug":"kangaroo","title":"කැන්ගරු","phrases":[]},{"slug":"turtle","title":"කැස්බෑවා","phrases":[]},{"slug":"giraffe","title":"ජිරාෆ්","phrases":[{"type":"👀","phrase":"මම ජිරාෆ් කෙනෙක් දැක්කා."}]},{"slug":"frog","title":"ගෙම්බා","phrases":[]},{"slug":"swan","title":"හංසයා","phrases":[]},{"slug":"spider","title":"මකුළුවා","phrases":[]},{"slug":"cow","title":"එළදෙන","phrases":[]},{"slug":"duck","title":"තාරාවා","phrases":[]},{"slug":"horse","title":"අශ්වයා","phrases":[]},{"slug":"chicken","title":"කුකුල් මස්","phrases":[]},{"slug":"bee","title":"මී මැසි","phrases":[{"type":"👀","phrase":"මම මී මැස්සෙක් දැක්කා."}]},{"slug":"pig","title":".රු","phrases":[]},{"slug":"dove","title":"එය කොහේ ද","phrases":[{"type":"🔊","phrase":"පරෙවියෙකු කරන ශබ්දය කුමක්ද?"}]},{"slug":"crab","title":"කකුළුවා","phrases":[{"type":"❤️","phrase":"මම කකුළුවන්ට කැමතියි."}]},{"slug":"penguin","title":"පෙන්ගුයින්","phrases":[]},{"slug":"elephant","title":"අලියා","phrases":[{"type":"👀","phrase":"මම අලියෙක් දැක්කා."}]},{"slug":"zebra","title":"සීබ්රා","phrases":[]},{"slug":"panda","title":"පැන්ඩා","phrases":[]},{"slug":"monkey","title":"වඳුරා","phrases":[]},{"slug":"camel","title":"ඔටුවා","phrases":[]},{"slug":"mouse","title":"මූසිකය","phrases":[]},{"slug":"tiger","title":"කොටියා","phrases":[]},{"slug":"jellyfish","title":"ජෙලිෆිෂ්","phrases":[]},{"slug":"crocodile","title":"කිඹුලා","phrases":[]},{"slug":"koala","title":"කෝලා","phrases":[]},{"slug":"ostrich","title":"පැස්බරා","phrases":[]},{"slug":"racoon","title":"රකූන්","phrases":[]},{"slug":"bat","title":"එක","phrases":[]},{"slug":"eagle","title":"රාජාලියා","phrases":[{"type":"❤️","phrase":"මම රාජාලීන්ට කැමතියි."},{"type":"🔊","phrase":"රාජාලියෙකු කරන ශබ්දය කුමක්ද?"}]},{"slug":"hippopotamus","title":"හිපපොටේමස්","phrases":[]},{"slug":"seal","title":"මුද්රාව","phrases":[]},{"slug":"walrus","title":"වොල්රස්","phrases":[]},{"slug":"seahorse","title":"මුහුදු අශ්වයා","phrases":[]},{"slug":"bull","title":"ගොනා","phrases":[]},{"slug":"pelican","title":"පෙලිකන්","phrases":[]},{"slug":"beaver","title":"බීවර්","phrases":[{"type":"🔊","phrase":"බීවර් කරන්නේ කුමන ශබ්දයද?"}]},{"slug":"goldfish","title":"ගෝල්ඩ්ෆිෂ්","phrases":[]},{"slug":"rhinoceros","title":"රයිනෝසරස්","phrases":[{"type":"❤️","phrase":"මම රයිනෝසරස් වලට කැමතියි."}]},{"slug":"snake","title":"සර්පයා","phrases":[]},{"slug":"lion","title":"සිංහයා","phrases":[]},{"slug":"squid","title":"දැල්ලා","phrases":[]},{"slug":"whale","title":"තල්මහ","phrases":[]},{"slug":"beetle","title":"කුරුමිණියා","phrases":[{"type":"👀","phrase":"මම කුරුමිණියා දුටුවෙමි."}]},{"slug":"dolphin","title":"ඩොල්ෆින්","phrases":[]},{"slug":"starfish","title":"තරු මාළු","phrases":[]},{"slug":"parakeet","title":"පැරකීට්","phrases":[]},{"slug":"owl","title":"බකමූණ","phrases":[{"type":"👀","phrase":"මම බකමූණෙක් දැක්කා."}]},{"slug":"sheep","title":"බැටළුවන්","phrases":[]}]