[{"slug":"basketball","title":"Basketball","phrases":[]},{"slug":"boxing","title":"Boksing","phrases":[]},{"slug":"tennis","title":"Tennis","phrases":[]},{"slug":"golf","title":"Golf","phrases":[]},{"slug":"hockey","title":"Hockey","phrases":[]},{"slug":"swimming","title":"Paglangoy","phrases":[]},{"slug":"baseball","title":"Baseball","phrases":[]},{"slug":"american-football","title":"American football","phrases":[]},{"slug":"cricket","title":"Cricket","phrases":[]},{"slug":"racing","title":"Karera","phrases":[]},{"slug":"skiing","title":"Pag-ski","phrases":[]},{"slug":"volleyball","title":"Volleyball","phrases":[]},{"slug":"fencing","title":"Fencing","phrases":[]},{"slug":"referee","title":"Tagahatol","phrases":[]},{"slug":"coach","title":"Coach","phrases":[]},{"slug":"kendo","title":"Kendo","phrases":[]},{"slug":"table-tennis","title":"Table ng tennis","phrases":[]},{"slug":"medal","title":"Medalya","phrases":[]},{"slug":"podium","title":"Podium","phrases":[]}]