[{"slug":"crayons","title":"crayons","phrases":[{"type":"тЭдя╕П","phrase":"ржЖржорж┐ ржХрзНрж░рж╛ржЗржУржи ржкржЫржирзНржж ржХрж░рж┐"},{"type":"ЁЯЩЛ","phrase":"ржЖржкржирж┐ ржЖржорж╛ржХрзЗ crayons ржжрж┐рждрзЗ ржкрж╛рж░рзЗржи?"},{"type":"ЁЯЦНя╕П","phrase":"ржЖржорж┐ ржЖржорж╛рж░ ржХрзНрж░рзЗржЗржиржЧрзБрж▓рж┐ ржмрзНржпржмрж╣рж╛рж░ ржХрж░рзЗ ржЖржБржХрждрзЗ ржЪрж╛ржЗред"}]},{"slug":"red","title":"рж▓рж╛рж▓","phrases":[{"type":"ЁЯСЙ","phrase":"ржПржЯрж╛ рж▓рж╛рж▓."},{"type":"ЁЯТЬ","phrase":"ржЖржорж╛рж░ ржкрзНрж░рж┐ржпрж╝ рж░ржЩ рж╣ржпрж╝ рж▓рж╛рж▓."},{"type":"ЁЯЩЛ","phrase":"ржЖржкржирж┐ ржЖржорж╛ржХрзЗ рж▓рж╛рж▓ ржкрзЗржЗржирзНржЯ ржжрж┐рждрзЗ ржкрж╛рж░рзЗржи?"}]},{"slug":"blue","title":"ржирзАрж▓","phrases":[{"type":"ЁЯСЙ","phrase":"ржПржЯрж╛ ржирзАрж▓."},{"type":"ЁЯТЬ","phrase":"ржЖржорж╛рж░ ржкрзНрж░рж┐ржпрж╝ рж░ржЩ ржирзАрж▓ред"},{"type":"ЁЯЩЛ","phrase":"ржЖржкржирж┐ ржЖржорж╛ржХрзЗ ржирзАрж▓ рж░ржЩ ржжрж┐рждрзЗ ржкрж╛рж░рзЗржи?"}]},{"slug":"orange","title":"ржХржорж▓рж╛","phrases":[{"type":"ЁЯСЙ","phrase":"ржПржЯрж┐ ржХржорж▓рж╛ рж░ржЩрзЗрж░ред"},{"type":"ЁЯТЬ","phrase":"ржЖржорж╛рж░ ржкрзНрж░рж┐ржпрж╝ рж░ржЩ ржХржорж▓рж╛ред"},{"type":"ЁЯЩЛ","phrase":"ржЖржкржирж┐ ржЖржорж╛ржХрзЗ ржХржорж▓рж╛ рж░ржЩ ржжрж┐рждрзЗ ржкрж╛рж░рзЗржи?"}]},{"slug":"green","title":"рж╕ржмрзБржЬ","phrases":[{"type":"ЁЯСЙ","phrase":"ржПржЯрж╛ рж╕ржмрзБржЬ."},{"type":"ЁЯТЬ","phrase":"ржЖржорж╛рж░ ржкрзНрж░рж┐ржпрж╝ рж░ржЩ рж╕ржмрзБржЬ."},{"type":"ЁЯЩЛ","phrase":"ржЖржкржирж┐ ржЖржорж╛ржХрзЗ рж╕ржмрзБржЬ ржкрзЗржЗржирзНржЯ ржжрж┐рждрзЗ ржкрж╛рж░рзЗржи?"}]},{"slug":"yellow","title":"рж╣рж▓рзБржж","phrases":[{"type":"ЁЯСЙ","phrase":"ржПржЯрж╛ рж╣рж▓рзБржж."},{"type":"ЁЯТЬ","phrase":"ржЖржорж╛рж░ ржкрзНрж░рж┐ржпрж╝ рж░ржЩ рж╣рж▓рзБржжред"},{"type":"ЁЯЩЛ","phrase":"ржЖржкржирж┐ ржХрж┐ ржЖржорж╛ржХрзЗ рж╣рж▓рзБржж рж░ржЩ ржжрж┐рждрзЗ ржкрж╛рж░рзЗржи?"}]},{"slug":"purple","title":"рж░ржХрзНрждржмрж░рзНржг","phrases":[{"type":"ЁЯСЙ","phrase":"ржПржЯрж┐ ржмрзЗржЧрзБржирж┐ред"},{"type":"ЁЯТЬ","phrase":"ржмрзЗржЧрзБржирж┐ рж░ржВ ржЖржорж╛рж░ ржкржЫржирзНржжрзЗрж░ рж░ржВ."},{"type":"ЁЯЩЛ","phrase":"ржЖржкржирж┐ ржЖржорж╛ржХрзЗ ржмрзЗржЧрзБржирж┐ ржкрзЗржЗржирзНржЯ ржжрж┐рждрзЗ ржкрж╛рж░рзЗржи?"}]},{"slug":"pink","title":"ржкрж░рж╛ржХрж╛рж╖рзНржарж╛","phrases":[{"type":"ЁЯСЙ","phrase":"ржПржЯрж┐ ржЧрзЛрж▓рж╛ржкрзАред"},{"type":"ЁЯТЬ","phrase":"ржЖржорж╛рж░ ржкрзНрж░рж┐ржпрж╝ рж░ржЩ ржЧрзЛрж▓рж╛ржкрзАред"},{"type":"ЁЯЩЛ","phrase":"ржЖржкржирж┐ ржЖржорж╛ржХрзЗ ржЧрзЛрж▓рж╛ржкрзА рж░ржЩ ржжрж┐рждрзЗ ржкрж╛рж░рзЗржи?"}]},{"slug":"brown","title":"ржмрж╛ржжрж╛ржорзА","phrases":[{"type":"ЁЯСЙ","phrase":"ржПржЯрж╛ ржмрж╛ржжрж╛ржорзА."},{"type":"ЁЯТЬ","phrase":"ржЖржорж╛рж░ ржкрзНрж░рж┐ржпрж╝ рж░ржЩ ржмрж╛ржжрж╛ржорзАред"},{"type":"ЁЯЩЛ","phrase":"ржЖржкржирж┐ ржЖржорж╛ржХрзЗ ржмрзНрж░рж╛ржЙржи ржкрзЗржЗржирзНржЯ ржжрж┐рждрзЗ ржкрж╛рж░рзЗржи?"}]},{"slug":"black","title":"ржХрж╛рж▓рзЛ","phrases":[{"type":"ЁЯСЙ","phrase":"ржПржЯрж╛ ржХрж╛рж▓рзЛ."},{"type":"ЁЯТЬ","phrase":"ржЖржорж╛рж░ ржкрзНрж░рж┐ржпрж╝ рж░ржЩ ржХрж╛рж▓рзЛред"},{"type":"ЁЯЩЛ","phrase":"ржЖржкржирж┐ ржЖржорж╛ржХрзЗ ржХрж╛рж▓рзЛ ржкрзЗржЗржирзНржЯ ржжрж┐рждрзЗ ржкрж╛рж░рзЗржи?"}]},{"slug":"white","title":"рж╕рж╛ржжрж╛","phrases":[{"type":"ЁЯСЙ","phrase":"ржЗрж╣рж╛ рж╕рж╛ржжрж╛."},{"type":"ЁЯТЬ","phrase":"ржЖржорж╛рж░ ржкрзНрж░рж┐ржпрж╝ рж░ржЩ рж╕рж╛ржжрж╛ред"},{"type":"ЁЯЩЛ","phrase":"ржЖржкржирж┐ ржЖржорж╛ржХрзЗ рж╕рж╛ржжрж╛ ржкрзЗржЗржирзНржЯ ржжрж┐рждрзЗ ржкрж╛рж░рзЗржи?"}]},{"slug":"gray","title":"ржзрзВрж╕рж░","phrases":[{"type":"ЁЯСЙ","phrase":"ржПржЯрж┐ ржзрзВрж╕рж░ред"},{"type":"ЁЯТЬ","phrase":"ржЖржорж╛рж░ ржкрзНрж░рж┐ржпрж╝ рж░ржЩ ржзрзВрж╕рж░ред"},{"type":"ЁЯЩЛ","phrase":"ржЖржкржирж┐ ржЖржорж╛ржХрзЗ ржзрзВрж╕рж░ рж░ржЩ ржжрж┐рждрзЗ ржкрж╛рж░рзЗржи?"}]},{"slug":"transparent","title":"рж╕рзНржмржЪрзНржЫ","phrases":[{"type":"ЁЯСЙ","phrase":"ржПржЯрж╛ рж╕рзНржмржЪрзНржЫред"},{"type":"ЁЯСА","phrase":"ржЖржорж┐ рж╕рзНржмржЪрзНржЫ рж░ржЩрзЗрж░ ржкрж┐ржЫржирзЗ ржжрзЗржЦрждрзЗ ржкрж╛ржЪрзНржЫрж┐ред"},{"type":"ЁЯЩЛ","phrase":"ржЖржкржирж┐ ржЖржорж╛ржХрзЗ ржорзБржЫрждрзЗ рж╕рж╛рж╣рж╛ржпрзНржп ржХрж░рждрзЗ ржкрж╛рж░рзЗржи?"}]},{"slug":"cyan","title":"рж╕рж╛ржпрж╝рж╛ржи","phrases":[{"type":"ЁЯСЙ","phrase":"ржПржЯрж╛ рж╕рж╛ржпрж╝рж╛ржиред"},{"type":"ЁЯТЬ","phrase":"ржЖржорж╛рж░ ржкрзНрж░рж┐ржпрж╝ рж░ржЩ рж╕рж╛ржпрж╝рж╛ржиред"},{"type":"ЁЯЩЛ","phrase":"ржЖржкржирж┐ ржЖржорж╛ржХрзЗ рж╕рж╛ржпрж╝рж╛ржи ржкрзЗржЗржирзНржЯ ржжрж┐рждрзЗ ржкрж╛рж░рзЗржи?"}]},{"slug":"violet","title":"ржмрзЗржЧрзБржирзА","phrases":[{"type":"ЁЯСЙ","phrase":"ржПржЯрж┐ ржмрзЗржЧрзБржирж┐ рж╣ржпрж╝ред"},{"type":"ЁЯТЬ","phrase":"ржЖржорж╛рж░ ржкрзНрж░рж┐ржпрж╝ рж░ржЩржЯрж┐ ржмрзЗржЧрзБржирж┐ред"},{"type":"ЁЯЩЛ","phrase":"ржЖржкржирж┐ ржЖржорж╛ржХрзЗ ржнрж╛ржпрж╝рзЛрж▓рзЗржЯ ржкрзЗржЗржирзНржЯ ржжрж┐рждрзЗ ржкрж╛рж░рзЗржи?"}]},{"slug":"turquoise","title":"ржлрж┐рж░рзЛржЬрж╛","phrases":[{"type":"ЁЯСЙ","phrase":"ржПржЯрж┐ ржлрж┐рж░рзЛржЬрж╛ред"},{"type":"ЁЯТЬ","phrase":"ржЖржорж╛рж░ ржкрзНрж░рж┐ржпрж╝ рж░ржЩ ржЯрж╛рж░рзНржХрзЛржЬ ose"},{"type":"ЁЯЩЛ","phrase":"ржЖржкржирж┐ ржЖржорж╛ржХрзЗ ржЯрж╛рж░рзНржХрзЛржЬ ржкрзЗржЗржирзНржЯ ржжрж┐рждрзЗ ржкрж╛рж░рзЗржи?"}]},{"slug":"lime","title":"ржЪрзБржи","phrases":[{"type":"ЁЯСЙ","phrase":"ржПржЯрж╛ ржЪрзБржиред"},{"type":"ЁЯТЬ","phrase":"ржЖржорж╛рж░ ржкрзНрж░рж┐ржпрж╝ рж░ржЩ ржЪрзБржиред"},{"type":"ЁЯЩЛ","phrase":"ржЖржкржирж┐ ржЖржорж╛ржХрзЗ ржЪрзБржи ржкрзЗржЗржирзНржЯ ржжрж┐рждрзЗ ржкрж╛рж░рзЗржи?"}]},{"slug":"plum","title":"ржмрж░ржЗ","phrases":[{"type":"ЁЯСЙ","phrase":"ржПржЯрж╛ ржмрж░ржЗред"},{"type":"ЁЯТЬ","phrase":"ржЖржорж╛рж░ ржкрзНрж░рж┐ржпрж╝ рж░ржЩ ржмрж░ржЗред"},{"type":"ЁЯЩЛ","phrase":"ржЖржорж╛ржХрзЗ ржкрзНрж▓рж╛ржо ржкрзЗржЗржирзНржЯ ржжрж┐рждрзЗ ржкрж╛рж░рзЗржи?"}]},{"slug":"tan","title":"рж╕рзБрждрж░рж╛ржВ","phrases":[{"type":"ЁЯСЙ","phrase":"ржПржЯрж┐ ржЯрзНржпрж╛ржи ржХрж╛рж▓рж╛рж░ред"},{"type":"ЁЯТЬ","phrase":"ржЖржорж╛рж░ ржкрзНрж░рж┐ржпрж╝ рж░ржЩ ржЯрзНржпрж╛ржи рж░ржЩред"},{"type":"ЁЯЩЛ","phrase":"ржЖржкржирж┐ ржЖржорж╛ржХрзЗ ржЯрзНржпрж╛ржи рж░ржЩрзЗрж░ ржкрзЗржЗржирзНржЯ ржжрж┐рждрзЗ ржкрж╛рж░рзЗржи?"}]},{"slug":"avocado","title":"ржЖржнрж╛ржХрж╛ржбрзЛ","phrases":[{"type":"ЁЯСЙ","phrase":"ржПржЯрж┐ ржЕрзНржпрж╛ржнрзЛржХрж╛ржбрзЛ рж░ржЩред"},{"type":"ЁЯТЬ","phrase":"ржЖржорж╛рж░ ржкрзНрж░рж┐ржпрж╝ рж░ржЩ ржЕрзНржпрж╛ржнрзЛржХрж╛ржбрзЛ рж░ржЩред"},{"type":"ЁЯЩЛ","phrase":"ржЖржкржирж┐ ржЖржорж╛ржХрзЗ ржЕрзНржпрж╛ржнрзЛржХрж╛ржбрзЛ рж░ржЩрж┐ржи ржкрзЗржЗржирзНржЯ ржжрж┐рждрзЗ ржкрж╛рж░рзЗржи?"}]},{"slug":"barbie-pink","title":"ржмрж╛рж░рзНржмрж┐ ржЧрзЛрж▓рж╛ржкрзА","phrases":[{"type":"ЁЯСЙ","phrase":"ржПржЯрж┐ ржмрж╛рж░ржмрж┐ ржЧрзЛрж▓рж╛ржкрзА рж░ржЩред"},{"type":"ЁЯТЬ","phrase":"ржЖржорж╛рж░ ржкрзНрж░рж┐ржпрж╝ рж░ржЩржЯрж┐ ржмрж╛рж░рзНржмрж┐ ржЧрзЛрж▓рж╛ржкрзАред"},{"type":"ЁЯЩЛ","phrase":"ржЖржкржирж┐ ржЖржорж╛ржХрзЗ ржмрж╛рж░рзНржмрж┐ ржЧрзЛрж▓рж╛ржкрзА ржкрзЗржЗржирзНржЯ ржжрж┐рждрзЗ ржкрж╛рж░рзЗржи?"}]},{"slug":"blizzard-blue","title":"ржмрж░ржл ржЭрж░рзНржгрж╛ ржирзАрж▓","phrases":[{"type":"ЁЯСЙ","phrase":"ржПржЯрж┐ ржмрж░ржлржЦржгрзНржб ржирзАрж▓ ржмрж░рзНржгрзЗрж░ред"},{"type":"ЁЯТЬ","phrase":"ржЖржорж╛рж░ ржкрзНрж░рж┐ржпрж╝ рж░ржЩ рж╣'рж▓ ржмрзНрж▓рж┐ржЬрж╛рж░рзНржб ржирзАрж▓ рж░ржЩред"},{"type":"ЁЯЩЛ","phrase":"рждрзБржорж┐ ржХрж┐ ржЖржорж╛ржХрзЗ ржмрзНрж▓рж┐ржЬрж╛рж░рзНржб ржмрзНрж▓рзБ ржкрзЗржЗржирзНржЯ ржжрж┐рждрзЗ ржкрж╛рж░ржмрзЗ?"}]}]